jetson_emulator/__init__.py
jetson_emulator/inference.py
jetson_emulator/utils.py
jetson_emulator-1.0.0.dist-info/LICENSE
jetson_emulator-1.0.0.dist-info/METADATA
jetson_emulator-1.0.0.dist-info/WHEEL
jetson_emulator-1.0.0.dist-info/top_level.txt
jetson_emulator-1.0.0.dist-info/RECORD
