Metadata-Version: 2.1
Name: jetson-emulator
Version: 1.0.0
Summary: Emulator of NVIDIA Jetson AI-computer for makers, learners, developers and students
Home-page: https://github.com/teavuihuang/jetson-emulator
Author: Tea Vui Huang
Author-email: tvhuang@hotmail.com
License: MIT
Keywords: deep-learning GPU jetson emulator AI edge-computing computer vision inference image classification object detection segmentation
Platform: UNKNOWN
Classifier: Development Status :: 5 - Production/Stable
Classifier: Intended Audience :: Developers
Classifier: Intended Audience :: Education
Classifier: Intended Audience :: Science/Research
Classifier: License :: OSI Approved :: MIT License
Classifier: Operating System :: Microsoft :: Windows
Classifier: Operating System :: POSIX :: Linux
Classifier: Programming Language :: Python
Classifier: Programming Language :: Python :: 3
Classifier: Topic :: Scientific/Engineering :: Artificial Intelligence
Classifier: Topic :: Software Development
Classifier: Topic :: System :: Hardware
Classifier: Topic :: Scientific/Engineering :: Image Recognition
Classifier: Topic :: System :: Emulators
Classifier: Environment :: GPU :: NVIDIA CUDA
Requires-Python: >=3.7.9
Requires-Dist: matplotlib (>=3.2.2)
Requires-Dist: numpy (>=1.18.5)
